pyModelChecking/__init__.py
pyModelChecking/graph.py
pyModelChecking/kripke.py
pyModelChecking/language.py
pyModelChecking/parser.py
pyModelChecking/BDD/BDD.py
pyModelChecking/BDD/OBDD.py
pyModelChecking/BDD/__init__.py
pyModelChecking/BDD/ordering.py
pyModelChecking/CTL/__init__.py
pyModelChecking/CTL/language.py
pyModelChecking/CTL/model_checking.py
pyModelChecking/CTL/parser.py
pyModelChecking/CTLS/__init__.py
pyModelChecking/CTLS/language.py
pyModelChecking/CTLS/model_checking.py
pyModelChecking/CTLS/parser.py
pyModelChecking/LTL/__init__.py
pyModelChecking/LTL/language.py
pyModelChecking/LTL/model_checking.py
pyModelChecking/LTL/parser.py
pyModelChecking/PL/__init__.py
pyModelChecking/PL/language.py
pyModelChecking/PL/parser.py
pyModelChecking/tests/__init__.py
pyModelChecking/tests/test_CTLS_language.py
pyModelChecking/tests/test_CTLS_modelchecking.py
pyModelChecking/tests/test_CTLS_parser.py
pyModelChecking/tests/test_CTL_language.py
pyModelChecking/tests/test_CTL_modelchecking.py
pyModelChecking/tests/test_CTL_parser.py
pyModelChecking/tests/test_LTL_language.py
pyModelChecking/tests/test_LTL_modelchecking.py
pyModelChecking/tests/test_LTL_parser.py
pyModelChecking/tests/test_OBDD.py
pyModelChecking/tests/test_graph.py
pyModelChecking/tests/test_kripke.py
pyModelChecking-1.3.4.dist-info/LICENSE
pyModelChecking-1.3.4.dist-info/METADATA
pyModelChecking-1.3.4.dist-info/WHEEL
pyModelChecking-1.3.4.dist-info/top_level.txt
pyModelChecking-1.3.4.dist-info/RECORD
