Metadata-Version: 2.1
Name: pyModelChecking
Version: 1.3.4
Summary: A simple Python model checking package
Home-page: https://github.com/albertocasagrande/pyModelChecking
Author: Alberto Casagrande
Author-email: acasagrande@units.it
License: GNU General Public License, version 2
Project-URL: Documentation, https://readthedocs.org/projects/pymodelchecking/
Project-URL: Source Code, https://github.com/albertocasagrande/pyModelChecking
Keywords: model checking temporal logics kripke structure
Classifier: Development Status :: 4 - Beta
Classifier: Environment :: Console
Classifier: Intended Audience :: Developers
Classifier: Intended Audience :: Information Technology
Classifier: Topic :: Scientific/Engineering
Classifier: Programming Language :: Python
Classifier: Programming Language :: Python :: 3.6
Classifier: Operating System :: OS Independent
Classifier: License :: OSI Approved :: GNU General Public License v2 (GPLv2)
Requires-Python: >=3.6
License-File: LICENSE
Requires-Dist: lark-parser
